scidatacontainer_db/__init__.py
scidatacontainer_db/admin.py
scidatacontainer_db/api_views.py
scidatacontainer_db/apps.py
scidatacontainer_db/models.py
scidatacontainer_db/parsers.py
scidatacontainer_db/serializers.py
scidatacontainer_db/test_utils.py
scidatacontainer_db/urls.py
scidatacontainer_db/utils.py
scidatacontainer_db/views.py
scidatacontainer_db/migrations/0001_initial.py
scidatacontainer_db/migrations/__init__.py
scidatacontainer_db/static/scidatacontainer_db/css/bootstrap.css
scidatacontainer_db/static/scidatacontainer_db/css/drag-drop.css
scidatacontainer_db/static/scidatacontainer_db/js/apikeys.js
scidatacontainer_db/static/scidatacontainer_db/js/bootstrap.js
scidatacontainer_db/static/scidatacontainer_db/js/bootstrap.js.map
scidatacontainer_db/static/scidatacontainer_db/js/drag-drop.js
scidatacontainer_db/static/scidatacontainer_db/js/jquery.min.js
scidatacontainer_db/static/scidatacontainer_db/js/popper.min.js
scidatacontainer_db/static/scidatacontainer_db/restful_api/css/bootstrap.min.css
scidatacontainer_db/templates/rest_framework/api.html
scidatacontainer_db/templates/scidatacontainer_db/apikeys.html
scidatacontainer_db/templates/scidatacontainer_db/base.html
scidatacontainer_db/templates/scidatacontainer_db/detail.html
scidatacontainer_db/templates/scidatacontainer_db/index.html
scidatacontainer_db/templates/scidatacontainer_db/invalidation_modal.html
scidatacontainer_db/templates/scidatacontainer_db/login.html
scidatacontainer_db/templates/scidatacontainer_db/menu.html
scidatacontainer_db/templates/scidatacontainer_db/messages.html
scidatacontainer_db/templates/scidatacontainer_db/navbar.html
scidatacontainer_db/templates/scidatacontainer_db/pagination.html
scidatacontainer_db/templates/scidatacontainer_db/update_permissions.html
scidatacontainer_db/templates/scidatacontainer_db/update_permissions_groups.html
scidatacontainer_db/templates/scidatacontainer_db/update_permissions_users.html
scidatacontainer_db/tests/__init__.py
django_scidatacontainer-0.2.1.dist-info/LICENSE
django_scidatacontainer-0.2.1.dist-info/METADATA
django_scidatacontainer-0.2.1.dist-info/WHEEL
django_scidatacontainer-0.2.1.dist-info/top_level.txt
django_scidatacontainer-0.2.1.dist-info/RECORD
