Metadata-Version: 2.1
Name: django-scidatacontainer
Version: 0.2.1
Summary: A Django webserver to handle SciDataConatiner.
Author-email: Sven Kleinert <sven.kleinert@phoenixd.uni-hannover.de>
License: GNU AFFERO GENERAL PUBLIC LICENSE
Classifier: Environment :: Web Environment
Classifier: Framework :: Django
Classifier: Framework :: Django :: 4.1
Classifier: License :: OSI Approved :: GNU Affero General Public License v3
Classifier: Operating System :: OS Independent
Classifier: Programming Language :: Python
Classifier: Programming Language :: Python :: 3
Classifier: Programming Language :: Python :: 3 :: Only
Classifier: Programming Language :: Python :: 3.8
Classifier: Programming Language :: Python :: 3.9
Classifier: Topic :: Internet :: WWW/HTTP
Classifier: Topic :: Internet :: WWW/HTTP :: Dynamic Content
Classifier: Topic :: Scientific/Engineering
Requires-Python: >=3.8
License-File: LICENSE
Requires-Dist: Django (>=4.1.3)
Requires-Dist: django-filter (>=22.1)
Requires-Dist: django-guardian (>=2.4.0)
Requires-Dist: djangorestframework (>=3.14.0)
Requires-Dist: django-rest-knox (>=4.2.0)
Requires-Dist: packaging (>=23.0)
Requires-Dist: python-magic (>=0.4.27)
Requires-Dist: SciDataContainer (>=1.0.0)
